genera/__init__.py
genera/apps/__init__.py
genera/apps/activate.py
genera/apps/fragment_amp/__init__.py
genera/apps/fragment_amp/app.json
genera/apps/fragment_amp/fragment_amp_app.py
genera/apps/fragment_amp/algo/__init__.py
genera/apps/fragment_amp/algo/algo.json
genera/apps/fragment_amp/algo/fragment_amp_algo.py
genera/apps/fragment_amp/data/__init__.py
genera/apps/fragment_amp/data/data.json
genera/apps/fragment_amp/data/fragment_amp_data.py
genera/apps/fragment_amp/device/__init__.py
genera/apps/fragment_amp/plot/__init__.py
genera/apps/fragment_amp/ui/__init__.py
genera/apps/fragment_amp/ui/fragment_amp_ui.py
genera/apps/fragment_amp/ui/ui.json
genera/apps/primer_generator/__init__.py
genera/apps/primer_generator/app.json
genera/apps/primer_generator/primer_generator_app.py
genera/apps/primer_generator/algo/__init__.py
genera/apps/primer_generator/algo/algo.json
genera/apps/primer_generator/algo/primer_generator_algo.py
genera/apps/primer_generator/data/__init__.py
genera/apps/primer_generator/data/data.json
genera/apps/primer_generator/data/primer_generator_data.py
genera/apps/primer_generator/device/__init__.py
genera/apps/primer_generator/plot/__init__.py
genera/apps/primer_generator/ui/__init__.py
genera/apps/primer_generator/ui/primer_generator_ui.py
genera/apps/primer_generator/ui/ui.json
genera/classes/__init__.py
genera/classes/algo.py
genera/classes/app.py
genera/classes/data.py
genera/classes/device.py
genera/classes/plot.py
genera/classes/test.py
genera/classes/ui.py
genera/ui/__init__.py
genera/ui/layout.py
genera/ui/root.py
genera/utils/__init__.py
genera/utils/options.py
genera/utils/settings.py
genera-0.1.14.dist-info/METADATA
genera-0.1.14.dist-info/WHEEL
genera-0.1.14.dist-info/top_level.txt
genera-0.1.14.dist-info/RECORD
