Metadata-Version: 2.1
Name: genera
Version: 0.1.14
Requires-Python: >=3.10
Requires-Dist: numpy >=1.20.0
Requires-Dist: scipy >=1.10.0
Requires-Dist: pandas >=2.1.0
Requires-Dist: biopython >=1.80
Requires-Dist: primer3-py >=2.0.0
Requires-Dist: openpyxl >=3.1.0
